README.md
setup.cfg
setup.py
prename/__init__.py
prename/prename.py
prename.egg-info/PKG-INFO
prename.egg-info/SOURCES.txt
prename.egg-info/dependency_links.txt
prename.egg-info/entry_points.txt
prename.egg-info/top_level.txt