Metadata-Version: 1.1
Name: prename
Version: 1.1.0
Summary: Simple CLI tool for enacting regex renames
Home-page: https://github.com/giftig/prename
Author: Rob Moore
Author-email: giftiger.wunsch@xantoria.com
License: UNKNOWN
Download-URL: https://github.com/giftig/prename/archive/1.0.tar.gz
Keywords: rename,renamer,regex renamer,regex,cli
Platform: UNKNOWN
